py_google_shopping/__init__.py
py_google_shopping/account_shipping.py
py_google_shopping/merchant.py
py_google_shopping/mixins.py
py_google_shopping/oauth.py
py_google_shopping/product_statuses.py
py_google_shopping/products.py
py_google_shopping/utils.py
py_google_shopping-0.2.2.dist-info/LICENSE
py_google_shopping-0.2.2.dist-info/METADATA
py_google_shopping-0.2.2.dist-info/NOTICE
py_google_shopping-0.2.2.dist-info/WHEEL
py_google_shopping-0.2.2.dist-info/top_level.txt
py_google_shopping-0.2.2.dist-info/RECORD
