Metadata-Version: 2.1
Name: py-google-shopping
Version: 0.2.2
Summary: Python client for Google Shopping API
Home-page: https://moatsystems.com
Author: Moat Systems Limited
Author-email: hi@moatsystems.com
License: MIT
Keywords: google shopping content api merchant product python
Platform: UNKNOWN
Classifier: Intended Audience :: Developers
Classifier: License :: DFSG approved
Classifier: License :: OSI Approved :: BSD License
Classifier: Operating System :: OS Independent
Classifier: Programming Language :: Python :: 2.7
Classifier: Programming Language :: Python :: 3
Classifier: Programming Language :: Python :: 3.4
Classifier: Programming Language :: Python :: 3.5
Classifier: Programming Language :: Python :: 3.6
Classifier: Topic :: Software Development :: Libraries :: Python Modules
Requires-Dist: requests
